Seraphin/Seraphin.py
Seraphin/__init__.py
Seraphin/__main__.py
Seraphin/tools.py
src/Seraphin.py
src/__init__.py
src/__main__.py
src/tools.py
Seraphin-0.0.4.dist-info/LICENSE
Seraphin-0.0.4.dist-info/METADATA
Seraphin-0.0.4.dist-info/WHEEL
Seraphin-0.0.4.dist-info/entry_points.txt
Seraphin-0.0.4.dist-info/top_level.txt
Seraphin-0.0.4.dist-info/RECORD
