Metadata-Version: 2.1
Name: Seraphin
Version: 0.0.4
Summary: true random generator
Home-page: https://github.com/ym001/Seraphin
Author: Yves Mercadier
Author-email: Yves Mercadier <info@realpython.com>
License: MIT License
Project-URL: Homepage, https://github.com/ym001/Seraphin
Keywords: feed,PRGN,random
Classifier: License :: OSI Approved :: MIT License
Classifier: Programming Language :: Python
Classifier: Programming Language :: Python :: 3
Requires-Python: >=3.0
License-File: LICENSE
Provides-Extra: dev
Requires-Dist: black ; extra == 'dev'
Requires-Dist: bumpver ; extra == 'dev'
Requires-Dist: isort ; extra == 'dev'
Requires-Dist: pip-tools ; extra == 'dev'
Requires-Dist: pytest ; extra == 'dev'
